handy_uti/__init__.py
handy_uti/apn_tester.py
handy_uti/astrobro_updater.py
handy_uti/direct_link.py
handy_uti/groq_models.py
handy_uti/launcher.py
handy_uti/main.py
handy_uti/md2epub.py
handy_uti/mistral_ocr.py
handy_uti/pypi_name_checker.py
handy_uti/rm_drm.py
handy_uti/style.css
handy_uti/token_counter.py
handy_uti/ui.py
handy_uti/utils.py
handy_uti/deDRM/__init__.py
handy_uti/deDRM/adobekey.py
handy_uti/deDRM/ineptepub.py
handy_uti/deDRM/ineptpdf.py
handy_uti/static/baloo.woff
handy_uti/static/handy-logo.svg
handy_uti/static/handy-utils-banner.png
handy_uti/yt_transcriber/__init__.py
handy_uti/yt_transcriber/utils.py
handy_uti-0.5.2.dist-info/METADATA
handy_uti-0.5.2.dist-info/WHEEL
handy_uti-0.5.2.dist-info/entry_points.txt
handy_uti-0.5.2.dist-info/licenses/LICENSE
handy_uti-0.5.2.dist-info/RECORD
