Metadata-Version: 2.4
Name: handy-uti
Version: 0.5.2
Summary: Handy Utilities For Daily Life Hacks
Project-URL: repository, https://github.com/hoishing/handy-uti
Author-email: Kelvin Ng <hoishing@gmail.com>
License: MIT
License-File: LICENSE
Requires-Python: >=3.12
Requires-Dist: beautifulsoup4>=4.13.4
Requires-Dist: click>=8.2.1
Requires-Dist: ebooklib>=0.19
Requires-Dist: google-genai
Requires-Dist: groq>=0.24.0
Requires-Dist: lxml>=5.4.0
Requires-Dist: mistralai
Requires-Dist: pycryptodome==3.21.0
Requires-Dist: pyjwt>=2.10.1
Requires-Dist: pypandoc-binary>=1.15
Requires-Dist: python-dotenv>=1.1.1
Requires-Dist: pytubefix
Requires-Dist: streamlit
Requires-Dist: transformers>=4.53.1
Requires-Dist: watchdog>=6.0.0
Requires-Dist: yt-dlp>=2025.6.9
